{
  "html": [
    {
      "name": "Label",
      "title": "HTML标签"
    },
    {
      "name": "Html_entity",
      "title": "HTML 字符实体"
    },
    {
      "name": "Html5",
      "title": "HTML5"
    },
    {
      "name": "Event",
      "title": "HTML事件属性"
    },
    {
      "name": "Meta",
      "title": "Meta"
    }
  ],
  "css": [
    {
      "name": "Total",
      "title": "CSS"
    },
    {
      "name": "Selector",
      "title": "CSS选择器"
    },
    {
      "name": "Flex",
      "title": "Flex"
    }
  ],
  "js": [
    {
      "name": "ES8",
      "title": "ES8"
    },
    {
      "name": "ES7",
      "title": "ES7"
    },
    {
      "name": "ES6",
      "title": "ES6"
    },
    {
      "name": "ES5",
      "title": "ES5"
    },
    {
      "name": "ES3",
      "title": "ES3"
    },
    {
      "name": "Strict-Mode",
      "title": "严格模式"
    },
    {
      "name": "Vue",
      "title": "Vue"
    },
    {
      "name": "React",
      "title": "React"
    },
    {
      "name": "Redux",
      "title": "Redux"
    },
    {
      "name": "React-Native",
      "title": "React Native"
    },
    {
      "name": "Angular",
      "title": "Angular"
    },
    {
      "name": "Reduce",
      "title": "Reduce的应用"
    },
    {
      "name": "Npm",
      "title": "Npm"
    },
    {
      "name": "Yarn",
      "title": "Yarn"
    },
    {
      "name": "RegExp",
      "title": "RegExp"
    },
    {
      "name": "History",
      "title": "Javascript的历史"
    },
    {
      "name": "Code",
      "title": "JS代码片段"
    },
    {
      "name": "Canvas",
      "title": "Canvas"
    },
    {
      "name": "Ajax",
      "title": "Ajax"
    },
    {
      "name": "Fetch",
      "title": "Fetch"
    },
    {
      "name": "Body",
      "title": "Body"
    },
    {
      "name": "Headers",
      "title": "Headers"
    },
    {
      "name": "Request",
      "title": "Request"
    },
    {
      "name": "Response",
      "title": "Response"
    },
    {
      "name": "Promise",
      "title": "Promise"
    },
    {
      "name": "Event",
      "title": "Event"
    },
    {
      "name": "Error",
      "title": "Error"
    },
    {
      "name": "KeyWord",
      "title": "关键字"
    },
    {
      "name": "ReservedWord",
      "title": "保留字"
    },
    {
      "name": "JQ",
      "title": "JQ API"
    },
    {
      "name": "DOM",
      "title": "DOM"
    },
    {
      "name": "Storage",
      "title": "Storage"
    },
    {
      "name": "Fullscreenchange",
      "title": "Fullscreenchange"
    },
    {
      "name": "Notification",
      "title": "Notification"
    },
    {
      "name": "Tinify.js",
      "title": "Tinify.js"
    },
    {
      "name": "Prettier.js",
      "title": "Prettier.js"
    },
    {
      "name": "js-beautify",
      "title": "js-beautify"
    },
    {
      "name": "Console",
      "title": "Console"
    }
  ],
  "node": [
    {
      "name": "overview",
      "title": "overview"
    },
    {
      "name": "global",
      "title": "global"
    },
    {
      "name": "console",
      "title": "console"
    },
    {
      "name": "buffer",
      "title": "buffer"
    },
    {
      "name": "path",
      "title": "path"
    },
    {
      "name": "querystring",
      "title": "querystring"
    },
    {
      "name": "url",
      "title": "url"
    },
    {
      "name": "stream",
      "title": "stream"
    },
    {
      "name": "fs",
      "title": "fs"
    },
    {
      "name": "os",
      "title": "os"
    },
    {
      "name": "readline",
      "title": "readline"
    },
    {
      "name": "package-fav",
      "title": "npm package 收藏夹"
    },
    {
      "name": "package-top",
      "title": "npm package top200"
    }
  ],
  "tool": [
    {
      "name": "Git",
      "title": "Git使用介绍"
    },
    {
      "name": "ProjectGuide",
      "title": "项目规范"
    },
    {
      "name": "CodeGuide",
      "title": "代码规范"
    },
    {
      "name": "Terminal",
      "title": "Terminal"
    },
    {
      "name": "SQL",
      "title": "SQL"
    },
    {
      "name": "Mongodb",
      "title": "Mongodb"
    },
    {
      "name": "Emmet",
      "title": "Emmet"
    },
    {
      "name": "English",
      "title": "English"
    },
    {
      "name": "Gem",
      "title": "Gem"
    },
    {
      "name": "Gitbook",
      "title": "Gitbook"
    },
    {
      "name": "Jekyll",
      "title": "Jekyll"
    },
    {
      "name": "Mac",
      "title": "Mac"
    },
    {
      "name": "Markdown",
      "title": "Markdown"
    },
    {
      "name": "Smarty",
      "title": "Smarty"
    },
    {
      "name": "Software",
      "title": "Software"
    },
    {
      "name": "Sublime",
      "title": "Sublime"
    }
  ],
  "assemble": [
    {
      "name": "Nav",
      "title": "前端资源导航"
    },
    {
      "name": "About",
      "title": "About Me"
    }
  ]
}
